monoscope_flask/__init__.py
monoscope_flask-1.0.0.dist-info/METADATA
monoscope_flask-1.0.0.dist-info/WHEEL
monoscope_flask-1.0.0.dist-info/top_level.txt
monoscope_flask-1.0.0.dist-info/RECORD
