Metadata-Version: 2.1
Name: monoscope-flask
Version: 1.0.0
Summary: A Flask SDK for Monoscope integration
Author: Monoscope
Author-email: hello@apitoolkit.io
Requires-Dist: Flask
Requires-Dist: monoscope-common
Requires-Dist: opentelemetry-api>=1.0.0
